earth2_api_wrapper/__init__.py
earth2_api_wrapper/cli.py
earth2_api_wrapper/client.py
earth2_api_wrapper/rate_limiter.py
earth2_api_wrapper-0.2.1.dist-info/METADATA
earth2_api_wrapper-0.2.1.dist-info/WHEEL
earth2_api_wrapper-0.2.1.dist-info/entry_points.txt
earth2_api_wrapper-0.2.1.dist-info/top_level.txt
earth2_api_wrapper-0.2.1.dist-info/RECORD
