Metadata-Version: 2.4
Name: earth2-api-wrapper
Version: 0.2.1
Summary: Unofficial Earth2 API wrapper with CLI (Python). Includes comprehensive safeguards to protect Earth2's bandwidth.
Author: 
License-Expression: MIT
Keywords: earth2,api,wrapper
Requires-Python: >=3.9
Requires-Dist: httpx>=0.27
Requires-Dist: typer>=0.12
Requires-Dist: rich>=13.0.0
Requires-Dist: tabulate>=0.9.0
